{
    "part1" : {
        "enable": true,
        "POINTS" : 50,
        "ACTIVATIONS" : ["relu"],
        "COLORS" : ["red", "blue"],
        "WIDTHS" : [100, 500],
        "DEPTHS" : [2, 4],
        "SEED_LIST" : [10, 32, 5],
        "OUT_DIM" : 1
    },
    "part2": {
        "enable" : false
        
    },
    "part3" : {
        "enable": true,
        "ACTIVATIONS" : ["relu", "rbf", "gabor"],
        "COLORS" : ["red", "blue"],
        "WIDTHS" : [100, 500],
        "DEPTHS" : [4],
        "SEED_LIST" : [10, 32, 5],
        "OUT_DIMS" : [10, 20]
    }   
}